CHANGES.rst
MANIFEST.in
README.rst
setup.py
src/cykooz/__init__.py
src/cykooz.djangopaste.egg-info/PKG-INFO
src/cykooz.djangopaste.egg-info/SOURCES.txt
src/cykooz.djangopaste.egg-info/dependency_links.txt
src/cykooz.djangopaste.egg-info/entry_points.txt
src/cykooz.djangopaste.egg-info/namespace_packages.txt
src/cykooz.djangopaste.egg-info/not-zip-safe
src/cykooz.djangopaste.egg-info/requires.txt
src/cykooz.djangopaste.egg-info/top_level.txt
src/cykooz/djangopaste/__init__.py