Metadata-Version: 1.1
Name: cykooz.djangopaste
Version: 1.1
Summary: A wrapper that allows us to run Django under PasteDeploy
Home-page: https://bitbucket.org/cykooz/cykooz.djangopaste
Author: Cykooz
Author-email: saikuz@mail.ru
License: BSD-derived
Keywords: web application server wsgi django
Platform: UNKNOWN
Classifier: Intended Audience :: Developers
Classifier: Programming Language :: Python
Classifier: Framework :: Django
Classifier: Topic :: Internet :: WWW/HTTP
Classifier: Topic :: Internet :: WWW/HTTP :: Dynamic Content
Classifier: Topic :: Internet :: WWW/HTTP :: WSGI
Classifier: Topic :: Internet :: WWW/HTTP :: WSGI :: Application
